flowbio/__init__.py
flowbio/client.py
flowbio/mutations.py
flowbio/pipelines.py
flowbio/queries.py
flowbio/samples.py
flowbio/upload.py
flowbio-0.3.4.dist-info/LICENSE
flowbio-0.3.4.dist-info/METADATA
flowbio-0.3.4.dist-info/WHEEL
flowbio-0.3.4.dist-info/top_level.txt
flowbio-0.3.4.dist-info/RECORD
