Metadata-Version: 2.1
Name: flowbio
Version: 0.3.4
Summary: A client for the Flow API.
Home-page: https://github.com/goodwright/flowbio
Author: Sam Ireland
Author-email: sam@goodwright.com
License: MIT
Keywords: nextflow bioinformatics pipeline
Platform: UNKNOWN
Classifier: Development Status :: 4 - Beta
Classifier: Topic :: Internet :: WWW/HTTP
Classifier: Intended Audience :: Developers
Classifier: License :: OSI Approved :: MIT License
Classifier: Topic :: Scientific/Engineering :: Bio-Informatics
Classifier: Programming Language :: Python :: 3
Classifier: Programming Language :: Python :: 3.8
Classifier: Programming Language :: Python :: 3.9
Classifier: Programming Language :: Python :: 3.10
Classifier: Programming Language :: Python :: 3.11
Classifier: Programming Language :: Python :: 3.12
Classifier: Programming Language :: Python :: 3.13
Requires-Python: !=2.*, !=3.0.*, !=3.1.*, !=3.2.*, !=3.3.*, !=3.4.*, !=3.5.*, !=3.6.*, !=3.7.*
License-File: LICENSE
Requires-Dist: tqdm
Requires-Dist: kirjava
Requires-Dist: requests
